<annotation>
	<folder>40</folder>
	<filename>00040_00000_00009.png</filename>
	<path>/Users/Angyu/Downloads/gtsrb-german-traffic-sign/Train/40/00040_00000_00009.png</path>
	<source>
		<database>Unknown</database>
	</source>
	<size>
		<width>44</width>
		<height>40</height>
		<depth>3</depth>
	</size>
	<segmented>0</segmented>
	<object>
		<name>Roundabout mandatory</name>
		<pose>Unspecified</pose>
		<truncated>0</truncated>
		<difficult>0</difficult>
		<bndbox>
			<xmin>6</xmin>
			<ymin>5</ymin>
			<xmax>40</xmax>
			<ymax>37</ymax>
		</bndbox>
	</object>
</annotation>
